cyberwave_robotics_integrations/__init__.py
cyberwave_robotics_integrations/base_robot.py
cyberwave_robotics_integrations/factory.py
cyberwave_robotics_integrations/input_controller.py
cyberwave_robotics_integrations/registry.py
cyberwave_robotics_integrations/cli/__init__.py
cyberwave_robotics_integrations/cli/app.py
cyberwave_robotics_integrations/drivers/__init__.py
cyberwave_robotics_integrations/drivers/kuka_kr3_driver.py
cyberwave_robotics_integrations/drivers/so100_driver.py
cyberwave_robotics_integrations/drivers/so_arm100_driver.py
cyberwave_robotics_integrations/drivers/spot_driver.py
cyberwave_robotics_integrations/drivers/tello_driver.py
cyberwave_robotics_integrations/examples/cli_usage_examples.py
cyberwave_robotics_integrations/examples/driver_integration_demo.py
cyberwave_robotics_integrations/examples/robot_driver_example.py
cyberwave_robotics_integrations/tests/test_cli_auto_register.py
cyberwave_robotics_integrations/tests/test_cli_cmd.py
cyberwave_robotics_integrations/tests/test_cli_start_stop.py
cyberwave_robotics_integrations/tests/test_cli_video.py
cyberwave_robotics_integrations/tests/test_factory.py
cyberwave_robotics_integrations/tests/test_factory_so100.py
cyberwave_robotics_integrations/tests/test_factory_so_arm100.py
cyberwave_robotics_integrations/tests/test_input_controller.py
cyberwave_robotics_integrations/tests/test_record_video.py
cyberwave_robotics_integrations/tests/test_sdk_integration.py
cyberwave_robotics_integrations/tests/test_so100_driver.py
cyberwave_robotics_integrations/tests/test_so_arm100_driver.py
cyberwave_robotics_integrations/tests/test_spot_driver.py
cyberwave_robotics_integrations/tests/test_tello_cli.py
cyberwave_robotics_integrations/tests/test_web_routes.py
cyberwave_robotics_integrations/web/__init__.py
cyberwave_robotics_integrations/web/static/dashboard.js
cyberwave_robotics_integrations/web/templates/dashboard.html
cyberwave_robotics_integrations-0.1.1.dist-info/METADATA
cyberwave_robotics_integrations-0.1.1.dist-info/WHEEL
cyberwave_robotics_integrations-0.1.1.dist-info/entry_points.txt
cyberwave_robotics_integrations-0.1.1.dist-info/top_level.txt
cyberwave_robotics_integrations-0.1.1.dist-info/RECORD
