Metadata-Version: 2.4
Name: cyberwave-robotics-integrations
Version: 0.1.1
Summary: Robot driver interfaces and CLI plugin for Cyberwave
Author-email: Simone Di Somma <sdisomma@cyberwave.com>
License: MIT
Project-URL: Homepage, https://github.com/cyberwave-os/cyberwave-python-robotics-integrations
Project-URL: Repository, https://github.com/cyberwave-os/cyberwave-python-robotics-integrations
Project-URL: Issues, https://github.com/cyberwave-os/cyberwave-python-robotics-integrations/issues
Project-URL: Documentation, https://github.com/cyberwave-os/cyberwave-python-robotics-integrations#readme
Keywords: robotics,digital-twin,automation,drivers,cli
Classifier: Development Status :: 4 - Beta
Classifier: Intended Audience :: Developers
Classifier: License :: OSI Approved :: MIT License
Classifier: Operating System :: OS Independent
Classifier: Programming Language :: Python :: 3
Classifier: Programming Language :: Python :: 3.9
Classifier: Programming Language :: Python :: 3.10
Classifier: Programming Language :: Python :: 3.11
Classifier: Programming Language :: Python :: 3.12
Classifier: Topic :: Scientific/Engineering :: Artificial Intelligence
Classifier: Topic :: Software Development :: Libraries :: Python Modules
Requires-Python: >=3.9
Requires-Dist: typer[all]>=0.12
Requires-Dist: rich>=13
